sanic_jinja/__init__.py
Sanic_Jinja-0.0.1.dist-info/LICENSE
Sanic_Jinja-0.0.1.dist-info/METADATA
Sanic_Jinja-0.0.1.dist-info/WHEEL
Sanic_Jinja-0.0.1.dist-info/top_level.txt
Sanic_Jinja-0.0.1.dist-info/RECORD
